npmai/__init__.py
npmai/npmai.py
npmai-0.1.4.dist-info/METADATA
npmai-0.1.4.dist-info/WHEEL
npmai-0.1.4.dist-info/top_level.txt
npmai-0.1.4.dist-info/RECORD
