Metadata-Version: 2.4
Name: npmai
Version: 0.1.4
Summary: A lightweight Ollama(no ollama installation needed) based LangChain-compatible LLM bridge ('LLaMA-3.2','CodeLLaMA-Instruct 7B','Gemma-2-Instruct 9B','Mistral 7B Instruct','Qwen-2.5-Coder 7B','Phi-3 Medium (8B)','Falcon 7B Instruct','Baichuan-2-7B','InternLM-Chat-7B','Vicuna 7B') built by Sonu Kumar.
Author-email: "Sonu Kumar (Viral Boy Bihar)" <sonuramashishnpm@gmail.com>
License: MIT
Project-URL: Homepage, https://npmai.onrender.com
Project-URL: Source, https://github.com/sonuramashishnpm/npmai
Requires-Python: <3.14,>=3.10
Requires-Dist: requests
Requires-Dist: langchain-core
